[
  {
    "name": "Nike Air Max 270",
    "quantity": 50,
    "releaseDate": "2023-03-15",
    "brand": "Nike",
    "model": "Air Max 270",
    "style": "Running",
    "size": "US 9",
    "color": "Black",
    "price": 129.99,
    "image": "https://img.freepik.com/free-vector/blue-tennis-shoes-sport-icon_18591-82518.jpg?w=1480&t=st=1706118801~exp=1706119401~hmac=0176a55b543ad5e76e7d277842c8396b0de56cd5ec503d6dbedb80ea9444e2b0",
    "material": "fabric",
    "stock_alert": 10
  },
  {
    "name": "Adidas Ultraboost 21",
    "quantity": 40,
    "releaseDate": "2023-02-28",
    "brand": "Adidas",
    "model": "Ultraboost 21",
    "style": "Performance",
    "size": "US 8.5",
    "color": "White",
    "price": 149.99,
    "image": "https://img.freepik.com/free-photo/shoes_1203-8155.jpg?w=1800&t=st=1706118811~exp=1706119411~hmac=838976473ad782de6cf5633688714623da1b64e3b4fc62a917b12b29754b18de",
    "material": "fabric",
    "stock_alert": 10
  },
  {
    "name": "Puma RS-X Retro",
    "quantity": 30,
    "releaseDate": "2023-04-10",
    "brand": "Puma",
    "model": "RS-X Retro",
    "style": "Lifestyle",
    "size": "US 10",
    "color": "Blue",
    "price": 89.99,
    "image": "https://img.freepik.com/free-psd/sport-shoe-mockup-isolated_1310-1632.jpg?w=1800&t=st=1706118822~exp=1706119422~hmac=9c104d5bed090de89a15227c8e84075ac471c48f739a6a647a6d021075a0363a",
    "material": "fabric",
    "stock_alert": 10
  },
  {
    "name": "New Balance 990v5",
    "quantity": 25,
    "releaseDate": "2023-01-20",
    "brand": "New Balance",
    "model": "990v5",
    "style": "Casual",
    "size": "US 7",
    "color": "Grey",
    "price": 179.99,
    "image": "https://img.freepik.com/free-photo/men-shoes_1203-8389.jpg?w=1800&t=st=1706118987~exp=1706119587~hmac=54d1d089880c2371bdbc17aea1d6192daba22ad7676de609a526d0dad8900e94",
    "material": "fabric",
    "stock_alert": 10
  },
  {
    "name": "Converse Chuck 70",
    "quantity": 60,
    "releaseDate": "2023-05-05",
    "brand": "Converse",
    "model": "Chuck 70",
    "style": "Classic",
    "size": "US 11",
    "color": "White",
    "price": 59.99,
    "image": "https://img.freepik.com/free-photo/new-pair-white-sneakers-isolated-white_93675-133039.jpg?w=1800&t=st=1706118989~exp=1706119589~hmac=6f0581ee0e199eed9e0b091354594a090e95d2a3aed82282fd440f3a9db9bce5",
    "material": "fabric",
    "stock_alert": 10
  },
  {
    "name": "Reebok Classic Leather",
    "quantity": 35,
    "releaseDate": "2023-03-01",
    "brand": "Reebok",
    "model": "Classic Leather",
    "style": "Heritage",
    "size": "US 9.5",
    "color": "Black",
    "price": 74.99,
    "image": "https://img.freepik.com/free-photo/men-shoes_1203-8652.jpg?w=1800&t=st=1706118804~exp=1706119404~hmac=cee2fe2db2efad0bdbe96e72f4ca0a0d5994513b5442f0a11438d234297671d4",
    "material": "fabric",
    "stock_alert": 10
  },
  {
    "name": "Vans Old Skool",
    "quantity": 45,
    "releaseDate": "2023-02-10",
    "brand": "Vans",
    "model": "Old Skool",
    "style": "Skate",
    "size": "US 8",
    "color": "Checkerboard",
    "price": 64.99,
    "image": "https://img.freepik.com/free-photo/pair-trainers_144627-3810.jpg?w=1800&t=st=1706118820~exp=1706119420~hmac=fd0861687512e211f2292033506ed25da4b1db870f0091e3d45f507c16ec895e",
    "material": "fabric",
    "stock_alert": 10
  },
  {
    "name": "Under Armour HOVR Phantom",
    "quantity": 20,
    "releaseDate": "2023-04-22",
    "brand": "Under Armour",
    "model": "HOVR Phantom",
    "style": "Running",
    "size": "US 10.5",
    "color": "Grey",
    "price": 129.99,
    "image": "https://img.freepik.com/free-photo/sport-new-lifestyle-fashion-sneakers_1203-6399.jpg?w=1800&t=st=1706118825~exp=1706119425~hmac=b386202a9e8e576c030f7d68b53f181834a922b16ce9b8846f53c8a1d3e2a106",
    "material": "fabric",
    "stock_alert": 10
  },
  {
    "name": "ASICS Gel-Kayano 27",
    "quantity": 15,
    "releaseDate": "2023-01-15",
    "brand": "ASICS",
    "model": "Gel-Kayano 27",
    "style": "Performance",
    "size": "US 7.5",
    "color": "White",
    "price": 159.99,
    "image": "https://img.freepik.com/free-photo/sport-shoes-running_1203-7549.jpg?w=1800&t=st=1706118995~exp=1706119595~hmac=0c72cafb0cd6fbcb242e9651d55295adde5d5389af92534d6f4117b22f19b793",
    "material": "fabric",
    "stock_alert": 10
  },
  {
    "name": "Skechers D'Lites",
    "quantity": 55,
    "releaseDate": "2023-05-20",
    "brand": "Skechers",
    "model": "D'Lites",
    "style": "Athleisure",
    "size": "US 9",
    "color": "Pink",
    "price": 54.99,
    "image": "https://img.freepik.com/free-photo/new-black-sneakers-isolated-white-background_93675-135051.jpg?w=1800&t=st=1706119004~exp=1706119604~hmac=20d8e1b8133bcb71035d3bb43e4b17f6719518f4ec4789eaf0d08a9001dfb0c4",
    "material": "fabric",
    "stock_alert": 10
  },
  {
    "name": "Nike React Element 55",
    "quantity": 48,
    "releaseDate": "2023-02-28",
    "brand": "Nike",
    "model": "React Element 55",
    "style": "Casual",
    "size": "US 8",
    "color": "Blue",
    "price": 119.99,
    "image": "https://img.freepik.com/free-photo/shoes-men-white-top-two_1203-6455.jpg?size=626&ext=jpg&ga=GA1.1.1856996481.1705401783&semt=ais",
    "material": "fabric",
    "stock_alert": 10
  },
  {
    "name": "Adidas NMD R1",
    "quantity": 36,
    "releaseDate": "2023-03-10",
    "brand": "Adidas",
    "model": "NMD R1",
    "style": "Urban",
    "size": "US 10",
    "color": "Black",
    "price": 169.99,
    "image": "https://img.freepik.com/free-photo/white-high-top-sneakers-unisex-footwear-fashion_53876-101515.jpg?size=626&ext=jpg&ga=GA1.1.1856996481.1705401783&semt=ais",
    "material": "fabric",
    "stock_alert": 10
  },
  {
    "name": "Puma Cali",
    "quantity": 28,
    "releaseDate": "2023-04-15",
    "brand": "Puma",
    "model": "Cali",
    "style": "Fashion",
    "size": "US 8.5",
    "color": "White",
    "price": 79.99,
    "image": "https://img.freepik.com/free-psd/view-bowling-shoes_23-2150953861.jpg?size=626&ext=jpg&ga=GA1.1.1856996481.1705401783&semt=ais",
    "material": "fabric",
    "stock_alert": 10
  },
  {
    "name": "New Balance Fresh Foam X",
    "quantity": 22,
    "releaseDate": "2023-01-25",
    "brand": "New Balance",
    "model": "Fresh Foam X",
    "style": "Running",
    "size": "US 7.5",
    "color": "Grey",
    "price": 139.99,
    "image": "https://img.freepik.com/free-photo/men-shoes_1203-8699.jpg?size=626&ext=jpg&ga=GA1.1.1856996481.1705401783&semt=ais",
    "material": "fabric",
    "stock_alert": 10
  },
  {
    "name": "Converse One Star",
    "quantity": 62,
    "releaseDate": "2023-05-08",
    "brand": "Converse",
    "model": "One Star",
    "style": "Streetwear",
    "size": "US 11.5",
    "color": "Black",
    "price": 69.99,
    "image": "https://img.freepik.com/free-photo/fashion-shoes-sneakers_1203-7528.jpg?size=626&ext=jpg&ga=GA1.1.1856996481.1705401783&semt=ais",
    "material": "fabric",
    "stock_alert": 10
  },
  {
    "name": "Reebok Nano X",
    "quantity": 32,
    "releaseDate": "2023-03-05",
    "brand": "Reebok",
    "model": "Nano X",
    "style": "CrossFit",
    "size": "US 9.5",
    "color": "Blue",
    "price": 119.99,
    "image": "",
    "material": "fabric",
    "stock_alert": 10
  },
  {
    "name": "Vans Slip-On",
    "quantity": 40,
    "releaseDate": "2023-02-15",
    "brand": "Vans",
    "model": "Slip-On",
    "style": "Casual",
    "size": "US 8",
    "color": "Checkerboard",
    "price": 54.99,
    "image": "https://img.freepik.com/free-photo/fashion-shoes_1203-7555.jpg?size=626&ext=jpg&ga=GA1.1.1856996481.1705401783&semt=ais",
    "material": "fabric",
    "stock_alert": 10
  }
]
